novem/__init__.py
novem/__main__.py
novem/api_ref.py
novem/applicator.py
novem/mail.py
novem/types.py
novem/utils.py
novem/version.py
novem/claim/__init__.py
novem/cli/__init__.py
novem/cli/common.py
novem/cli/config.py
novem/cli/editor.py
novem/cli/filter.py
novem/cli/gql.py
novem/cli/group.py
novem/cli/invite.py
novem/cli/setup.py
novem/cli/vis.py
novem/colors/__init__.py
novem/colors/colors.py
novem/exceptions/__init__.py
novem/group/__init__.py
novem/group/org.py
novem/group/org_group.py
novem/group/profile.py
novem/group/roles.py
novem/group/user_group.py
novem/job/__init__.py
novem/job/config.py
novem/repo/__init__.py
novem/repo/config.py
novem/shared/__init__.py
novem/table/__init__.py
novem/table/selector.py
novem/table/utils/__init__.py
novem/table/utils/format.py
novem/tags/__init__.py
novem/vis/__init__.py
novem/vis/cell.py
novem/vis/colors.py
novem/vis/custom.py
novem/vis/files.py
novem/vis/grid.py
novem/vis/mail.py
novem/vis/mail_sections.py
novem/vis/plot.py
novem/vis/plot_config.py
novem-0.5.7.dist-info/METADATA
novem-0.5.7.dist-info/WHEEL
novem-0.5.7.dist-info/entry_points.txt
novem-0.5.7.dist-info/licenses/LICENSE
novem-0.5.7.dist-info/RECORD
