Metadata-Version: 2.4
Name: novem
Version: 0.5.7
Summary: python library for the novem data visualisation platform
Project-URL: Homepage, https://novem.io
Project-URL: Repository, https://github.com/novem-code/novem-python
Author-email: Sondov Engen <sen@novem.io>, Bjørnar Snoksrud <bsn@novem.io>, Martin Myrseth <mmy@novem.io>
License-Expression: MIT
License-File: LICENSE
Requires-Python: <4,>=3.9
Requires-Dist: colorama>=0.4.6
Requires-Dist: packaging==25.0
Requires-Dist: pyreadline3>=3.5.4
Requires-Dist: requests>=2.32.4
Requires-Dist: typing-extensions>=4.14.1
Requires-Dist: urllib3>=2.5.0
